bitfactory/__init__.py
bitfactory/bitfactory.py
bitfactory/exceptions.py
bitfactory/mutators.py
bitfactory/py.typed
bitfactory-0.2.0.dist-info/WHEEL
bitfactory-0.2.0.dist-info/METADATA
bitfactory-0.2.0.dist-info/RECORD
