Metadata-Version: 2.3
Name: bitfactory
Version: 0.2.0
Summary: Create structured binary data easily.
Author: Nyz
Author-email: Nyz <nyz@bearswithsa.ws>
Classifier: Programming Language :: Python :: 3
Classifier: Programming Language :: Python :: 3.9
Classifier: Programming Language :: Python :: 3.10
Classifier: Programming Language :: Python :: 3.11
Classifier: Programming Language :: Python :: 3.12
Classifier: Programming Language :: Python :: 3.13
Classifier: Programming Language :: Python :: 3.14
Requires-Python: >=3.9, <4
